[
	{
		"league": "英格兰联赛锦标赛",
		"source": "extra",
		"ecid": "7592641",
		"num": "",
		"singleList": [
			false,
			false
		],
		"strong": "H",
		"dateTime": "11-15 03:00",
		"itemList": [
			{
				"oddsTitle": "独赢",
				"oddsItemList": [
					[
						"2.08"
					],
					[
						"2.92"
					],
					[
						"3.60"
					]
				]
			},
			{
				"oddsTitle": "让球",
				"oddsItemList": [
					[
						"-0/0.5",
						"1.860"
					],
					[
						"+0/0.5",
						"1.960"
					]
				]
			},
			{
				"oddsTitle": "得分",
				"oddsItemList": [
					[
						"-2.5/3",
						"1.880"
					],
					[
						"+2.5/3",
						"1.920"
					]
				]
			}
		],
		"teamList": [
			"什鲁斯伯里",
			"沃尔索尔"
		],
		"rate": 112
	},
	{
		"league": "英格兰联赛锦标赛",
		"source": "extra",
		"ecid": "7592601",
		"num": "",
		"singleList": [
			false,
			false
		],
		"strong": "H",
		"dateTime": "11-15 03:00",
		"itemList": [
			{
				"oddsTitle": "独赢",
				"oddsItemList": [
					[
						"1.84"
					],
					[
						"3.50"
					],
					[
						"3.65"
					]
				]
			},
			{
				"oddsTitle": "让球",
				"oddsItemList": [
					[
						"-0.5",
						"1.840"
					],
					[
						"+0.5",
						"1.980"
					]
				]
			},
			{
				"oddsTitle": "得分",
				"oddsItemList": [
					[
						"-2.5/3",
						"1.920"
					],
					[
						"+2.5/3",
						"1.880"
					]
				]
			}
		],
		"teamList": [
			"卡莱尔联",
			"哈洛贾特"
		],
		"rate": 110.83333333333333
	},
	{
		"league": "英格兰联赛锦标赛",
		"source": "extra",
		"ecid": "7592577",
		"num": "",
		"singleList": [
			false,
			false
		],
		"strong": "H",
		"dateTime": "11-15 03:00",
		"itemList": [
			{
				"oddsTitle": "独赢",
				"oddsItemList": [
					[
						"1.40"
					],
					[
						"5.90"
					],
					[
						"4.65"
					]
				]
			},
			{
				"oddsTitle": "让球",
				"oddsItemList": [
					[
						"-1/1.5",
						"1.960"
					],
					[
						"+1/1.5",
						"1.860"
					]
				]
			},
			{
				"oddsTitle": "得分",
				"oddsItemList": [
					[
						"-3",
						"1.910"
					],
					[
						"+3",
						"1.890"
					]
				]
			}
		],
		"teamList": [
			"布莱克浦",
			"莫康比"
		],
		"rate": 111.2
	},
	{
		"league": "英格兰联赛锦标赛",
		"source": "extra",
		"ecid": "7592691",
		"num": "",
		"singleList": [
			false,
			false
		],
		"strong": "H",
		"dateTime": "11-15 03:30",
		"itemList": [
			{
				"oddsTitle": "独赢",
				"oddsItemList": [
					[
						"2.36"
					],
					[
						"2.44"
					],
					[
						"3.75"
					]
				]
			},
			{
				"oddsTitle": "让球",
				"oddsItemList": [
					[
						"-0",
						"1.880"
					],
					[
						"+0",
						"1.940"
					]
				]
			},
			{
				"oddsTitle": "得分",
				"oddsItemList": [
					[
						"-3",
						"1.910"
					],
					[
						"+3",
						"1.890"
					]
				]
			}
		],
		"teamList": [
			"史托港",
			"博尔顿"
		],
		"rate": 111.4
	}
]